{"loaded_from_firestore": false, "total_pageviews": 1, "total_script_runs": 4, "total_time_seconds": 5.986322, "per_day": {"days": ["2023-08-09", "2023-08-10"], "pageviews": [0, 1], "script_runs": [0, 4]}, "widgets": {"Click me to celebrate!": 0, "Section": {"\ud83c\udfe0 Home": 3, "1\ufe0f\u20e3 Introduction": 0, "2\ufe0f\u20e3 Autograd": 0, "3\ufe0f\u20e3 More forward & backward functions": 0, "4\ufe0f\u20e3 Putting everything together": 0, "5\ufe0f\u20e3 Bonus": 0, "1\ufe0f\u20e3 Optimizers": 0, "2\ufe0f\u20e3 Weights and Biases": 0, "3\ufe0f\u20e3 Bonus": 0}}, "start_time": "10 Aug 2023, 10:28:30"}